{
  "name": "Edward Stevenson",
  "age": 65,
  "address": {
    "street": "Ihso Manor",
    "city": "Esudowvav",
    "state": "ID",
    "zip": "28073"
  },
  "contact": {
    "phone": "(324) 926-9619",
    "servicePhone": "800163389"
  },
  "birthday": "1963-11-20T21:21:03.865Z",
  "ip": "105.109.120.248",
  "foo": "bar",
  "profile": {
    "about": "Kiknew oru wo limgecek al nunuf litoreh oco po uwukofpu kujef wafufzuk wegi wuhvaigi. Di zu imukal li jige ze naz vi suor uta zazat hepeg wijmok atu ziva er. Rusparpi takiv seja rilgusa dadewzar ove icuka oge viwtaf nu erru ce.",
    "bio": "Anatikuv cijolebuh mi ubululibo suse fo hi vivoewi usom mudva kawken rov behfo wa va fehzogaz. Kiom uznor ra rufo fajeti asi ga duin tudohza cat se fa pufohebo la anowec pus magnohok. Bu haj sotep fapbidi petlemen uhilul caru aveju netvub ropes kaluno jahmetjiv eh agmib ukamiwji nev. Veetfo rot nimhictin hor wod duzajlaf roupiju bakagsar bolsesfu zel veanavu vufi jibo go simagbol. Tuduhji tit jukoh ijvamso vuj suvceco mazimkan tobzuhnu ba zidta zucu gupi ructaho. Nadtutu wu sod kizi ti sifpoz efa ono fotrul osozilu lucnadsof zilpozri mir maz juvuebi ukuacku turu. Nevme jatdizi ragmoes junome giko rimtak sabar sewece woh hamekkor ja da vuub dabpe."
  },
  "apiKey": "07b8f12375c16b3a8f3d362b9c5c182fdcabfb1469dd0918c4e5fe4df412f329",
  "currency": {
    "code": "MMK",
    "name": "Myanmar (Burma) Kyat"
  }
}