{
  "name": "Christine Cross",
  "age": 29,
  "address": {
    "street": "Dojed Pike",
    "city": "Kutifuj",
    "state": "HI",
    "zip": "01616"
  },
  "contact": {
    "phone": "(514) 425-8515",
    "servicePhone": "800669474"
  },
  "birthday": "1999-10-02T21:12:44.220Z",
  "ip": "65.151.8.25",
  "foo": "bar",
  "profile": {
    "about": "Ag sehop buz fu suj ud wef gowov ipnak ji lewote girmubuk nizguni hum kaje bosudal lomho. Bohlos jemove top jejioko gin efeteizu dilbufoti mo te zonwufzom hewap uladizda wicguhu feco atular. Mulwibav rakmez boojruf ruk el li ta kuh jiksirul ujog gaisa ozoinhis ezideomu. Omozuok noz oce masaha onudugta cosjec le onrab nowaptih kouru du ba hef jildec ovi uj oceha. Diruvcev ju reg obejew vaaz eso go cebposik raj pag weh de puk lepe numjoacu hutolji. Jepzu lebcugcol kajaga kub kevodo sudvav dudrupwa rokuf hovek emiuvujo bema dava mudkel ritut wuce fo ge nemzu. Veted sodza soh fohzizup eb eve vusapi sipicu iva rian ruftukna zol ru pimib tel.",
    "bio": "Sacbotbe falamis ab fuvnene ruva ri ju gewhewiw zosvolo nawicis uhtalup fegnufnik co fih pehrihfuj fa gicwer nekusjuf. Ele ji ven lewpifo povdutuc uwse duprukat tokciwi lecmaj gejif eb meulwe. Ubate cigeena uksowo mum tas ufizasha lazozlep nak hijfo wuk cinatif ba uddu ce po cin."
  },
  "apiKey": "47ee4d0b3f34ee61b9a9bd56202474ed0eec332aac461378f68a318718b56b7d",
  "currency": {
    "code": "NPR",
    "name": "Nepal Rupee"
  }
}